strwythura/__init__.py
strwythura/ctx.py
strwythura/elem.py
strwythura/ent.py
strwythura/erkg.py
strwythura/lex.py
strwythura/nlp.py
strwythura/opt.py
strwythura/prof.py
strwythura/rag.py
strwythura/resources/__init__.py
strwythura/resources/logo.png
strwythura/resources/pyvis.jinja2
strwythura/resources/senzing.png
strwythura/scrape.py
strwythura/vis.py
strwythura/work.py
strwythura-2.0.2.dist-info/METADATA
strwythura-2.0.2.dist-info/WHEEL
strwythura-2.0.2.dist-info/licenses/LICENSE
strwythura-2.0.2.dist-info/RECORD
