Metadata-Version: 2.4
Name: strwythura
Version: 2.0.2
Summary: Construct an entity-resolved knowledge graph from structured data sources and unstructured content sources, implementing an ontology pipeline, plus context engineering for optimizing AI application outcomes within a specific domain.
License-Expression: MIT
License-File: LICENSE
Keywords: air-gapped environment,computable semantics,context engineering,declarative LLM integration,domain context,entity embedding,entity linking,entity resolution,epistemic literacy,graph algorithms,graph analytics,graphrag,human-in-the-loop,interactive visualization,knowledge graph,named entity recognition,natural language processing,observability and optimization,ontology pipeline,relation extraction,retrieval-augmented generation,semantic expansion,semantic layer,semantic random walk,spec
Author: Paco Nathan
Author-email: paco@senzing.com
Requires-Python: >=3.11,<3.14
Classifier: Programming Language :: Python
Classifier: Programming Language :: Python :: 3 :: Only
Classifier: Programming Language :: Python :: 3.11
Classifier: Programming Language :: Python :: 3.12
Classifier: Programming Language :: Python :: 3.13
Classifier: Operating System :: OS Independent
Classifier: License :: OSI Approved :: MIT License
Classifier: Development Status :: 5 - Production/Stable
Classifier: Intended Audience :: Developers
Classifier: Intended Audience :: Education
Classifier: Intended Audience :: Information Technology
Classifier: Intended Audience :: Science/Research
Classifier: Topic :: Scientific/Engineering :: Artificial Intelligence
Classifier: Topic :: Scientific/Engineering :: Human Machine Interfaces
Classifier: Topic :: Scientific/Engineering :: Information Analysis
Classifier: Topic :: Software Development :: Libraries :: Python Modules
Classifier: Topic :: Text Processing :: Indexing
Requires-Dist: accelerate (>=1.10.1,<2.0.0)
Requires-Dist: arrowspace (>=0.13.3,<0.14.0)
Requires-Dist: bs4 (>=0.0.2,<0.0.3)
Requires-Dist: datamodel-code-generator (>=0.52.2,<0.53.0)
Requires-Dist: datasets (>=4.0.0,<5.0.0)
Requires-Dist: datasketch (>=1.8.0,<2.0.0)
Requires-Dist: dspy (>=3.1.2,<4.0.0)
Requires-Dist: gensim (>=4.3.3,<5.0.0)
Requires-Dist: gliner (>=0.2.21,<0.3.0)
Requires-Dist: gliner-spacy (>=0.0.11,<0.0.12)
Requires-Dist: icecream (>=2.1.8,<3.0.0)
Requires-Dist: jinja2 (>=3.1.6,<4.0.0)
Requires-Dist: lance-namespace (>=0.0.20)
Requires-Dist: lancedb (>=0.26)
Requires-Dist: lxml (>=6.0.0,<7.0.0)
Requires-Dist: networkx (>=3.5,<4.0)
Requires-Dist: nltk (>=3.9.1,<4.0.0)
Requires-Dist: numpy (>=1.17,<3.0.0)
Requires-Dist: opik (>=1.9.93,<2.0.0)
Requires-Dist: placekey (>=0.0.36,<0.0.37)
Requires-Dist: polars (>=1.32.3,<2.0.0)
Requires-Dist: psutil (>=7.2.0,<8.0.0)
Requires-Dist: pydantic (>=2.12.5,<3.0.0)
Requires-Dist: pyinstrument (>=5.0.3,<6.0.0)
Requires-Dist: pyshacl (>=0.30.1,<0.31.0)
Requires-Dist: pyvis (>=0.3.2,<0.4.0)
Requires-Dist: rdflib (>=7.4.0,<8.0.0)
Requires-Dist: requests (>=2.32.4,<3.0.0)
Requires-Dist: requests-cache (>=1.2.1,<2.0.0)
Requires-Dist: senzing-grpc (==0.5.11)
Requires-Dist: spacy (>=3.8.7,<4.0.0)
Requires-Dist: streamlit (>=1.52.2,<2.0.0)
Requires-Dist: sz-semantics (>=1.2.0,<2.0.0)
Requires-Dist: transformers (<4.57.0)
Requires-Dist: validators (>=0.35.0,<0.36.0)
Requires-Dist: w3lib (>=2.3.1,<3.0.0)
Requires-Dist: yfiles-graphs-for-streamlit (>=1.3.0,<2.0.0)
Project-URL: codes, https://github.com/DerwenAI/strwythura
Project-URL: cite, https://doi.org/10.5281/zenodo.16934079
Project-URL: quiz, https://derwen.ai/quiz/ai_def
Project-URL: slides, https://tinyurl.com/strwythura
Project-URL: tubes, https://youtu.be/ZWl5Pb29O-o
Project-URL: words, https://blog.derwen.ai/strwythura-2a8007af3682
Project-URL: wiki, https://deepwiki.com/DerwenAI/strwythura
